sanctumlabs/__init__.py
sanctumlabs/py.typed
sanctumlabs/messageschema/__init__.py
sanctumlabs/messageschema/common/__init__.py
sanctumlabs/messageschema/common/v1/__init__.py
sanctumlabs/messageschema/common/v1/address_pb2.py
sanctumlabs/messageschema/common/v1/address_pb2.pyi
sanctumlabs/messageschema/common/v1/location_pb2.py
sanctumlabs/messageschema/common/v1/location_pb2.pyi
sanctumlabs/messageschema/common/v1/money_pb2.py
sanctumlabs/messageschema/common/v1/money_pb2.pyi
sanctumlabs/messageschema/events/__init__.py
sanctumlabs/messageschema/events/common/__init__.py
sanctumlabs/messageschema/events/common/v1/__init__.py
sanctumlabs/messageschema/events/common/v1/common_pb2.py
sanctumlabs/messageschema/events/common/v1/common_pb2.pyi
sanctumlabs/messageschema/events/envelope/__init__.py
sanctumlabs/messageschema/events/envelope/v1/__init__.py
sanctumlabs/messageschema/events/envelope/v1/envelope_pb2.py
sanctumlabs/messageschema/events/envelope/v1/envelope_pb2.pyi
sanctumlabs/messageschema/events/notifications/__init__.py
sanctumlabs/messageschema/events/notifications/email/__init__.py
sanctumlabs/messageschema/events/notifications/email/v1/__init__.py
sanctumlabs/messageschema/events/notifications/email/v1/data_pb2.py
sanctumlabs/messageschema/events/notifications/email/v1/data_pb2.pyi
sanctumlabs/messageschema/events/notifications/email/v1/events_pb2.py
sanctumlabs/messageschema/events/notifications/email/v1/events_pb2.pyi
sanctumlabs/messageschema/events/notifications/sms/__init__.py
sanctumlabs/messageschema/events/notifications/sms/v1/__init__.py
sanctumlabs/messageschema/events/notifications/sms/v1/data_pb2.py
sanctumlabs/messageschema/events/notifications/sms/v1/data_pb2.pyi
sanctumlabs/messageschema/events/notifications/sms/v1/events_pb2.py
sanctumlabs/messageschema/events/notifications/sms/v1/events_pb2.pyi
sanctumlabs/messageschema/events/signup/__init__.py
sanctumlabs/messageschema/events/signup/v1/__init__.py
sanctumlabs_messageschema-0.9.0.dist-info/METADATA
sanctumlabs_messageschema-0.9.0.dist-info/WHEEL
sanctumlabs_messageschema-0.9.0.dist-info/top_level.txt
sanctumlabs_messageschema-0.9.0.dist-info/RECORD
